transfinite/__init__.py
transfinite/factorisation.py
transfinite/ordinal.py
transfinite/ordinal_factors.py
transfinite/util.py
transfinite-0.5.2.dist-info/METADATA
transfinite-0.5.2.dist-info/WHEEL
transfinite-0.5.2.dist-info/top_level.txt
transfinite-0.5.2.dist-info/RECORD
