Metadata-Version: 1.2
Name: transfinite
Version: 0.5.2
Summary: Transfinite ordinals for Python
Home-page: UNKNOWN
Author: Alex Riley
License: MIT
Project-URL: Source, https://github.com/ajcr/transfinite/
Project-URL: Tracker, https://github.com/ajcr/transfinite/issues
Keywords: set-theory ordinals arithmetic factorization LaTeX
Platform: UNKNOWN
Classifier: Topic :: Software Development :: Libraries :: Python Modules
Classifier: License :: OSI Approved :: MIT License
Classifier: Programming Language :: Python :: 3.6
Classifier: Programming Language :: Python :: 3.7
Classifier: Programming Language :: Python :: 3.8
Classifier: Programming Language :: Python :: 3.9
Requires-Python: >=3.6.0
